[
  {
    "fact": "           "
  },
  {
    "fact": "Η αγαπημένη σειρά του Τσακ Νόρις είναι το Κωνσταντίνου και Ελένης και γι'αυτό το δείχνει ακόμα ο ΑΝΤ1.Η αγαπημένη σειρά του Τσακ Νόρις είναι το Κωνσταντίνου και Ελένης και γι'αυτό το δείχνει ακόμα ο ΑΝΤ1.Η αγαπημένη σειρά του Τσακ Νόρις είναι το Κωνσταντίνου και Ελένης και γι'αυτό το δείχνει ακόμα ο ΑΝΤ1.Η αγαπημένη σειρά του Τσακ Νόρις είναι το Κωνσταντίνου και Ελένης και γι'αυτό το δείχνει ακόμα ο ΑΝΤ1.Η αγαπημένη σειρά του Τσακ Νόρις είναι το Κωνσταντίνου και Ελένης και γι'αυτό το δείχνει ακόμα ο ΑΝΤ1."
  },
  {
    "fact": "sadddddddddddddddddddddddddddd"
  },
  {
    "fact": "ssssssssssssssssssssssssssss"
  },
  {
    "fact": "Η αγαπημένη σειρά του Τσακ Νόρις είναι το Κωνσταντίνου και Ελένης και γι'αυτό το δείχνει ακόμα ο ΑΝΤ1.Η αγαπημένη σειρά του Τσακ Νόρις είναι το Κωνσταντίνου και Ελένης και γι'αυτό το δείχνει ακόμα ο ΑΝΤ1.Η αγαπημένη σειρά του Τσακ Νόρις είναι το Κωνσταντίνου και Ελένης και γι'αυτό το δείχνει ακόμα ο ΑΝΤ1.Η αγαπημένη σειρά του Τσακ Νόρις είναι το Κωνσταντίνου και Ελένης και γι'αυτό το δείχνει ακόμα ο ΑΝΤ1.Η αγαπημένη σειρά του Τσακ Νόρις είναι το Κωνσταντίνου και Ελένης και γι'αυτό το δείχνει ακόμα ο ΑΝΤ1.Η αγαπημένη σειρά του Τσακ Νόρις είναι το Κωνσταντίνου και Ελένης και γι'αυτό το δείχνει ακόμα ο ΑΝΤ1.Η αγαπημένη σειρά του Τσακ Νόρις είναι το Κωνσταντίνου και Ελένης και γι'αυτό το δείχνει ακόμα ο ΑΝΤ1.Η αγαπημένη σειρά του Τσακ Νόρις είναι το Κωνσταντίνου και Ελένης και γι'αυτό το δείχνει ακόμα ο ΑΝΤ1.Η αγαπημένη σειρά του Τσακ Νόρις είναι το Κωνσταντίνου και Ελένης και γι'αυτό το δείχνει ακόμα ο ΑΝΤ1."
  }
]